<PAMDataset>
  <Metadata domain="Esri">
    <MDI key="PyramidResamplingType">NEAREST</MDI>
  </Metadata>
  <PAMRasterBand band="1">
    <Histograms>
      <HistItem>
        <HistMin>10.19999980926514</HistMin>
        <HistMax>46.20000076293945</HistMax>
        <BucketCount>256</BucketCount>
        <IncludeOutOfRange>1</IncludeOutOfRange>
        <Approximate>0</Approximate>
        <HistCounts>2|0|0|0|1|0|0|0|0|0|1|0|2|0|0|2|0|0|1|1|1|0|1|0|2|2|4|4|3|10|4|17|11|19|42|25|60|35|84|47|66|126|70|162|83|76|200|93|235|109|139|266|112|250|123|296|148|163|372|185|362|215|234|460|251|566|292|318|606|360|716|386|797|465|492|1023|513|1110|586|630|1329|713|1449|784|846|1776|919|1923|1025|2139|1168|1184|2526|1341|2867|1382|1482|3014|1632|3451|1806|1817|3803|1893|3914|2007|3985|2120|2109|4304|2168|4474|2312|2362|4733|2601|5247|2739|2831|5767|2874|5977|3085|6294|3238|3274|6586|3306|6659|3423|3312|6775|3566|7392|3667|3715|7817|4054|8417|3860|7383|3711|3636|7620|3947|7638|3634|3511|6915|3394|6427|3152|3269|6429|3156|6224|3103|6555|3431|3380|7258|3754|7661|3797|3749|7802|3928|8128|4010|3841|7608|3669|7679|3892|7711|4026|4231|7978|3848|7770|4031|3989|7669|4007|7550|3661|3648|7286|3562|6723|3532|6465|2926|2950|5725|2717|5081|2318|2165|3980|1937|3771|1914|1831|3584|1613|3258|1574|3100|1556|1591|3484|1750|3391|1661|1627|3397|1734|3703|1979|1980|4037|1864|3812|1841|3635|1922|1830|3459|1756|3633|1800|1934|3445|1414|1818|594|489|787|206|284|113|267|153|150|330|162|340|169|151|260|83|123|52|32|1</HistCounts>
      </HistItem>
    </Histograms>
    <Metadata>
      <MDI key="STATISTICS_COVARIANCES">32.13880046757129</MDI>
      <MDI key="STATISTICS_EXCLUDEDVALUES"></MDI>
      <MDI key="STATISTICS_MAXIMUM">46.200000762939</MDI>
      <MDI key="STATISTICS_MEAN">32.491002024049</MDI>
      <MDI key="STATISTICS_MEDIAN">32.505883</MDI>
      <MDI key="STATISTICS_MINIMUM">10.199999809265</MDI>
      <MDI key="STATISTICS_SKIPFACTORX">1</MDI>
      <MDI key="STATISTICS_SKIPFACTORY">1</MDI>
      <MDI key="STATISTICS_STDDEV">5.6691093187176</MDI>
    </Metadata>
  </PAMRasterBand>
</PAMDataset>
